{"nodes": [{"id": "uploads_0af919cc_photo", "label": "Photo d'identit\u00e9 \u00e9tudiant - Document upload\u00e9 (CIP ou justificatif)", "file_type": "image", "source_file": "backend/uploads/0af919cc-eddc-46be-b3a1-09c2964004b2.jpg", "source_location": null, "source_url": null, "captured_at": null, "author": null, "contributor": null}, {"id": "upload_student_document_concept", "label": "Document \u00e9tudiant upload\u00e9 - Photo d'identit\u00e9 / pi\u00e8ce justificative", "file_type": "concept", "source_file": "backend/uploads/0af919cc-eddc-46be-b3a1-09c2964004b2.jpg", "source_location": null, "source_url": null, "captured_at": null, "author": null, "contributor": null}], "edges": [{"source": "uploads_0af919cc_photo", "target": "upload_student_document_concept", "relation": "conceptually_related_to", "confidence": "INFERRED", "confidence_score": 0.85, "source_file": "backend/uploads/0af919cc-eddc-46be-b3a1-09c2964004b2.jpg", "source_location": null, "weight": 0.8}, {"source": "uploads_0af919cc_photo", "target": "uploads_dir", "relation": "references", "confidence": "INFERRED", "confidence_score": 0.95, "source_file": "backend/uploads/0af919cc-eddc-46be-b3a1-09c2964004b2.jpg", "source_location": null, "weight": 1.0}], "hyperedges": []}